{
  "legislative_session": "2025",
  "identifier": "SB0755",
  "title": "Higher Education - Student Financial Assistance - Students in Informal Kinship Care Relationships",
  "from_organization": "~{\"classification\": \"upper\"}",
  "classification": [
    "bill"
  ],
  "subject": [],
  "abstracts": [],
  "other_titles": [],
  "other_identifiers": [],
  "actions": [
    {
      "description": "First Reading Education, Energy, and the Environment",
      "date": "2025-01-31",
      "organization_id": "~{\"classification\": \"upper\"}",
      "classification": [
        "referral-committee"
      ],
      "related_entities": []
    },
    {
      "description": "Hearing 2/21 at 1:00 p.m.",
      "date": "2025-02-05",
      "organization_id": "~{\"classification\": \"upper\"}",
      "classification": [],
      "related_entities": []
    },
    {
      "description": "Hearing canceled",
      "date": "2025-02-19",
      "organization_id": "~{\"classification\": \"upper\"}",
      "classification": [],
      "related_entities": []
    },
    {
      "description": "Hearing 2/21 at 9:30 a.m.",
      "date": "2025-02-19",
      "organization_id": "~{\"classification\": \"upper\"}",
      "classification": [],
      "related_entities": []
    }
  ],
  "sponsorships": [
    {
      "name": "A. Washington",
      "classification": "primary",
      "entity_type": "person",
      "primary": true,
      "person_id": "~{\"chamber\": \"upper\", \"name\": \"A. Washington\"}",
      "organization_id": null
    }
  ],
  "related_bills": [],
  "versions": [
    {
      "note": "First - Higher Education - Student Financial Assistance - Students in Informal Kinship Care Relationships",
      "links": [
        {
          "url": "http://mgaleg.maryland.gov/2025RS/bills/sb/sb0755f.pdf",
          "media_type": "application/pdf"
        }
      ],
      "date": "",
      "classification": ""
    }
  ],
  "documents": [
    {
      "note": "Fiscal and Policy Note",
      "links": [
        {
          "url": "http://mgaleg.maryland.gov/2025RS/fnotes/bil_0005/sb0755.pdf",
          "media_type": "application/pdf"
        }
      ],
      "date": "",
      "classification": ""
    }
  ],
  "citations": [],
  "sources": [
    {
      "url": "http://mgaleg.maryland.gov/mgawebsite/Legislation/Details/sb0755?ys=2025RS",
      "note": ""
    }
  ],
  "extras": {
    "date_effective": "July 1, 2025"
  },
  "jurisdiction": {
    "id": "ocd-jurisdiction/country:us/state:md/government",
    "name": "Maryland",
    "classification": "state",
    "division_id": "ocd-division/country:us/state:md"
  },
  "scraped_at": "2025-07-28T21:09:05+00:00",
  "_id": "1832461a-6bf7-11f0-9f1f-a6884ecab6f1"
}